{
  "title": ":",
  "tag": [
    "",
    "others"
  ],
  "features": "ER図（論理モデル、IE表記）",
  "elements": {},
  "overview_counts": {
    "entities": "3",
    "relationships": "2"
  },
  "powerpoint_en.png": {
    "drawing_method": "powerpoint",
    "lang": "en",
    "text": [],
    "text_count": 0
  },
  "powerpoint_ja.png": {
    "drawing_method": "powerpoint",
    "lang": "ja",
    "text": [],
    "text_count": 239
  },
  "handwritten_ja.png": {
    "drawing_method": "handwritten",
    "lang": "ja",
    "text": [],
    "text_count": 239
  },
  "whiteboard_ja.png": {
    "drawing_method": "whiteboard",
    "lang": "ja",
    "text": [],
    "text_count": 239
  }
}